MANIFEST.in
requirements.txt
setup.py
crux/__init__.py
crux/exc.py
crux/keystone.py
crux/main.py
crux/commands/__init__.py
crux/commands/base.py
crux/commands/endpoint_create.py
crux/commands/endpoint_list.py
crux/commands/tenant_create.py
crux/commands/user_create.py
crux/commands/user_list.py
keystone_crux.egg-info/PKG-INFO
keystone_crux.egg-info/SOURCES.txt
keystone_crux.egg-info/dependency_links.txt
keystone_crux.egg-info/entry_points.txt
keystone_crux.egg-info/pbr.json
keystone_crux.egg-info/requires.txt
keystone_crux.egg-info/top_level.txt