Metadata-Version: 1.0
Name: keystone-crux
Version: 7
Summary: A tool for manipulating Keystone
Home-page: http://github.com/larsks/crux
Author: Lars Kellogg-Stedman
Author-email: lars@oddbit.com
License: UNKNOWN
Platform: UNKNOWN
